ssb_client/__init__.py
ssb_client/feed/__init__.py
ssb_client/feed/models.py
ssb_client/muxrpc.py
ssb_client/packet_stream.py
ssb_client/tests/__init__.py
ssb_client/tests/test_feed.py
ssb_client/tests/test_packet_stream.py
ssb_client/tests/test_util.py
ssb_client/util.py
ssb_client-0.1.0.dist-info/LICENSE
ssb_client-0.1.0.dist-info/WHEEL
ssb_client-0.1.0.dist-info/METADATA
ssb_client-0.1.0.dist-info/RECORD
